spex/README.md
spex/__init__.py
spex/spherical_expansion.py
spex/utils.py
spex/angular/README.md
spex/angular/__init__.py
spex/angular/solid_harmonics.py
spex/angular/spherical_harmonics.py
spex/cutoff/README.md
spex/cutoff/__init__.py
spex/cutoff/shifted_cosine.py
spex/cutoff/step.py
spex/engine/README.md
spex/engine/__init__.py
spex/engine/dicts.py
spex/engine/serialize.py
spex/engine/spec.py
spex/engine/yaml.py
spex/metatensor/__init__.py
spex/metatensor/soap_power_spectrum.py
spex/metatensor/spherical_expansion.py
spex/radial/README.md
spex/radial/__init__.py
spex/radial/physical/__init__.py
spex/radial/physical/laplacian_eigenstates.py
spex/radial/physical/physical_basis.py
spex/radial/physical/spliner.py
spex/radial/physical/trimmed_and_splined.py
spex/radial/simple/__init__.py
spex/radial/simple/bernstein.py
spex/radial/simple/simple.py
spex/species/README.md
spex/species/__init__.py
spex/species/alchemical.py
spex/species/orthogonal.py
torch_spex-0.1.0.dist-info/WHEEL
torch_spex-0.1.0.dist-info/METADATA
torch_spex-0.1.0.dist-info/RECORD
