Metadata-Version: 2.4
Name: torch-spex
Version: 0.1.0
Summary: computing spherical expansions with pytorch
Author-email: Marcel Langer <dev@marcel.science>, Filippo Bigi <filippo.bigi@epfl.ch>, Paolo Pegolo <paolo.pegolo@epfl.ch>, Philip Loche <philip.loche@epfl.ch>
Requires-Python: >=3.9
Requires-Dist: numpy
Requires-Dist: PyYAML
Requires-Dist: scipy
Requires-Dist: sphericart[torch]
Requires-Dist: pytest ; extra == "dev"
Requires-Dist: ruff ; extra == "dev"
Requires-Dist: ase ; extra == "dev"
Requires-Dist: physical_basis ; extra == "dev"
Requires-Dist: vesin ; extra == "dev"
Requires-Dist: featomic ; extra == "dev"
Requires-Dist: metatensor-torch ; extra == "dev"
Requires-Dist: physical_basis ; extra == "physical"
Project-URL: Source, https://github.com/lab-cosmo/torch-spex
Provides-Extra: dev
Provides-Extra: physical
